README.rst
setup.py
apium/__init__.py
apium/base.py
apium/fields.py
apium/handlers/__init__.py
apium/handlers/django/__init__.py
apium/handlers/django/handler.py
apium/handlers/flask/__init__.py
apium/handlers/flask/handler.py
apium_dev.egg-info/PKG-INFO
apium_dev.egg-info/SOURCES.txt
apium_dev.egg-info/dependency_links.txt
apium_dev.egg-info/top_level.txt