Metadata-Version: 1.0
Name: apium-dev
Version: 0.1.1
Summary: Python JSON-RPC Framework
Home-page: https://apium.dev/
Author: Alexandr Katsko
Author-email: UNKNOWN
License: LGPLv3
Platform: UNKNOWN
